src/tpu/my_reg.sv
`timescale 1ns/1ps
module my_reg (
    input logic clk,
    input logic rst,
    input logic signed [15:0] d_in,
    input logic load,
    output logic signed [15:0] q_out
);

    always_ff @(posedge clk or posedge rst) begin
        if (rst) begin
            q_out <= 16'b0;
        end else if (load) begin
            q_out <= d_in;
        end
    end
endmodule

waveforms/my_reg.vcd
$date
	Fri Nov 28 11:56:24 2025
$end
$version
	Icarus Verilog
$end
$timescale
	1ps
$end
$scope module my_reg $end
$var wire 1 ! clk $end
$var wire 16 " d_in [15:0] $end
$var wire 1 # load $end
$var wire 1 $ rst $end
$var reg 16 % q_out [15:0] $end
$upscope $end
$enddefinitions $end
#0
$dumpvars
b0 %
0$
1#
b0 "
1!
$end
#5000
0!
#10000
b1001000110100 "
1!
#15000
0!
#20000
b1001000110100 %
1!
#21000
b1010101111001101 "
#25000
0!
#30000
b1010101111001101 %
1!
#31000
b1111111111111111 "
#35000
0!
#40000
b1111111111111111 %
1!
#41000
b0 "
#45000
0!
#50000
b0 %
1!
#51000
b111111111111111 "
#55000
0!
#60000
b111111111111111 %
1!
#61000
b1000000000000000 "
#65000
0!
#70000
b1000000000000000 %
1!
